just_mining_com_api.py
just_mining_com_api-0.0.1.dist-info/LICENSE
just_mining_com_api-0.0.1.dist-info/METADATA
just_mining_com_api-0.0.1.dist-info/WHEEL
just_mining_com_api-0.0.1.dist-info/top_level.txt
just_mining_com_api-0.0.1.dist-info/RECORD
