Metadata-Version: 2.1
Name: just-mining-com-api
Version: 0.0.1
Summary: Python wrapper for just-mining.com API
Home-page: https://github.com/PhunkyBob/just-mining-com-api
Author: Nicolas MARTIN
License: UNKNOWN
Project-URL: Bug Tracker, https://github.com/PhunkyBob/just-mining-com-api/issues
Platform: UNKNOWN
Classifier: Programming Language :: Python :: 3
Classifier: License :: OSI Approved :: GNU General Public License v3 (GPLv3)
Classifier: Operating System :: OS Independent
Requires-Python: >=3.6
License-File: LICENSE
Requires-Dist: requests
